{
  "kind": "SourceFile",
  "pos": {
    "offset": 0,
    "line": 1,
    "column": 1
  },
  "end": {
    "offset": 142,
    "line": 10,
    "column": 1
  },
  "children": [
    {
      "kind": "InterfaceDeclaration",
      "pos": {
        "offset": 0,
        "line": 1,
        "column": 1
      },
      "end": {
        "offset": 140,
        "line": 9,
        "column": 2
      },
      "children": [
        {
          "kind": "Identifier",
          "pos": {
            "offset": 78,
            "line": 6,
            "column": 10
          },
          "end": {
            "offset": 90,
            "line": 6,
            "column": 22
          },
          "text": "JSONSchema4"
        },
        {
          "kind": "PropertySignature",
          "pos": {
            "offset": 92,
            "line": 6,
            "column": 24
          },
          "end": {
            "offset": 106,
            "line": 7,
            "column": 13
          },
          "children": [
            {
              "kind": "Identifier",
              "pos": {
                "offset": 92,
                "line": 6,
                "column": 24
              },
              "end": {
                "offset": 97,
                "line": 7,
                "column": 4
              },
              "text": "a"
            },
            {
              "kind": "QuestionToken",
              "pos": {
                "offset": 97,
                "line": 7,
                "column": 4
              },
              "end": {
                "offset": 98,
                "line": 7,
                "column": 5
              },
              "text": "?"
            },
            {
              "kind": "NumberKeyword",
              "pos": {
                "offset": 99,
                "line": 7,
                "column": 6
              },
              "end": {
                "offset": 106,
                "line": 7,
                "column": 13
              },
              "text": "number"
            }
          ]
        },
        {
          "kind": "PropertySignature",
          "pos": {
            "offset": 106,
            "line": 7,
            "column": 13
          },
          "end": {
            "offset": 137,
            "line": 8,
            "column": 30
          },
          "children": [
            {
              "kind": "Identifier",
              "pos": {
                "offset": 106,
                "line": 7,
                "column": 13
              },
              "end": {
                "offset": 117,
                "line": 8,
                "column": 10
              },
              "text": "extends"
            },
            {
              "kind": "QuestionToken",
              "pos": {
                "offset": 117,
                "line": 8,
                "column": 10
              },
              "end": {
                "offset": 118,
                "line": 8,
                "column": 11
              },
              "text": "?"
            },
            {
              "kind": "UnionType",
              "pos": {
                "offset": 119,
                "line": 8,
                "column": 12
              },
              "end": {
                "offset": 137,
                "line": 8,
                "column": 30
              },
              "children": [
                {
                  "kind": "StringKeyword",
                  "pos": {
                    "offset": 119,
                    "line": 8,
                    "column": 12
                  },
                  "end": {
                    "offset": 126,
                    "line": 8,
                    "column": 19
                  },
                  "text": "string"
                },
                {
                  "kind": "ArrayType",
                  "pos": {
                    "offset": 128,
                    "line": 8,
                    "column": 21
                  },
                  "end": {
                    "offset": 137,
                    "line": 8,
                    "column": 30
                  },
                  "children": [
                    {
                      "kind": "StringKeyword",
                      "pos": {
                        "offset": 128,
                        "line": 8,
                        "column": 21
                      },
                      "end": {
                        "offset": 135,
                        "line": 8,
                        "column": 28
                      },
                      "text": "string"
                    }
                  ]
                }
              ]
            }
          ]
        }
      ]
    },
    {
      "kind": "EndOfFileToken",
      "pos": {
        "offset": 140,
        "line": 9,
        "column": 2
      },
      "end": {
        "offset": 142,
        "line": 10,
        "column": 1
      },
      "text": ""
    }
  ]
}
