{
  "kind": "SourceFile",
  "pos": {
    "offset": 0,
    "line": 1,
    "column": 1
  },
  "end": {
    "offset": 160,
    "line": 6,
    "column": 54
  },
  "children": [
    {
      "kind": "ClassDeclaration",
      "pos": {
        "offset": 0,
        "line": 1,
        "column": 1
      },
      "end": {
        "offset": 103,
        "line": 4,
        "column": 2
      },
      "children": [
        {
          "kind": "Identifier",
          "pos": {
            "offset": 25,
            "line": 2,
            "column": 6
          },
          "end": {
            "offset": 27,
            "line": 2,
            "column": 8
          },
          "text": "C"
        },
        {
          "kind": "Constructor",
          "pos": {
            "offset": 29,
            "line": 2,
            "column": 10
          },
          "end": {
            "offset": 100,
            "line": 3,
            "column": 70
          },
          "children": [
            {
              "kind": "Parameter",
              "pos": {
                "offset": 47,
                "line": 3,
                "column": 17
              },
              "end": {
                "offset": 76,
                "line": 3,
                "column": 46
              },
              "children": [
                {
                  "kind": "Identifier",
                  "pos": {
                    "offset": 47,
                    "line": 3,
                    "column": 17
                  },
                  "end": {
                    "offset": 59,
                    "line": 3,
                    "column": 29
                  },
                  "text": "defaultParam"
                },
                {
                  "kind": "BooleanKeyword",
                  "pos": {
                    "offset": 60,
                    "line": 3,
                    "column": 30
                  },
                  "end": {
                    "offset": 68,
                    "line": 3,
                    "column": 38
                  },
                  "text": "boolean"
                },
                {
                  "kind": "FalseKeyword",
                  "pos": {
                    "offset": 70,
                    "line": 3,
                    "column": 40
                  },
                  "end": {
                    "offset": 76,
                    "line": 3,
                    "column": 46
                  },
                  "text": "false"
                }
              ]
            },
            {
              "kind": "Block",
              "pos": {
                "offset": 97,
                "line": 3,
                "column": 67
              },
              "end": {
                "offset": 100,
                "line": 3,
                "column": 70
              }
            }
          ]
        }
      ]
    },
    {
      "kind": "FunctionDeclaration",
      "pos": {
        "offset": 103,
        "line": 4,
        "column": 2
      },
      "end": {
        "offset": 160,
        "line": 6,
        "column": 54
      },
      "children": [
        {
          "kind": "Identifier",
          "pos": {
            "offset": 115,
            "line": 6,
            "column": 9
          },
          "end": {
            "offset": 119,
            "line": 6,
            "column": 13
          },
          "text": "foo"
        },
        {
          "kind": "Parameter",
          "pos": {
            "offset": 120,
            "line": 6,
            "column": 14
          },
          "end": {
            "offset": 137,
            "line": 6,
            "column": 31
          },
          "children": [
            {
              "kind": "Identifier",
              "pos": {
                "offset": 120,
                "line": 6,
                "column": 14
              },
              "end": {
                "offset": 132,
                "line": 6,
                "column": 26
              },
              "text": "defaultParam"
            },
            {
              "kind": "FirstLiteralToken",
              "pos": {
                "offset": 134,
                "line": 6,
                "column": 28
              },
              "end": {
                "offset": 137,
                "line": 6,
                "column": 31
              },
              "text": "10"
            }
          ]
        },
        {
          "kind": "Block",
          "pos": {
            "offset": 157,
            "line": 6,
            "column": 51
          },
          "end": {
            "offset": 160,
            "line": 6,
            "column": 54
          }
        }
      ]
    },
    {
      "kind": "EndOfFileToken",
      "pos": {
        "offset": 160,
        "line": 6,
        "column": 54
      },
      "end": {
        "offset": 160,
        "line": 6,
        "column": 54
      },
      "text": ""
    }
  ]
}
