{
  "kind": "SourceFile",
  "pos": {
    "offset": 0,
    "line": 1,
    "column": 1
  },
  "end": {
    "offset": 1029,
    "line": 60,
    "column": 1
  },
  "children": [
    {
      "kind": "FirstStatement",
      "pos": {
        "offset": 0,
        "line": 1,
        "column": 1
      },
      "end": {
        "offset": 397,
        "line": 17,
        "column": 51
      },
      "children": [
        {
          "kind": "VariableDeclarationList",
          "pos": {
            "offset": 0,
            "line": 1,
            "column": 1
          },
          "end": {
            "offset": 396,
            "line": 17,
            "column": 50
          },
          "children": [
            {
              "kind": "VariableDeclaration",
              "pos": {
                "offset": 352,
                "line": 17,
                "column": 6
              },
              "end": {
                "offset": 396,
                "line": 17,
                "column": 50
              },
              "children": [
                {
                  "kind": "Identifier",
                  "pos": {
                    "offset": 352,
                    "line": 17,
                    "column": 6
                  },
                  "end": {
                    "offset": 364,
                    "line": 17,
                    "column": 18
                  },
                  "text": "MyComponent"
                },
                {
                  "kind": "ArrowFunction",
                  "pos": {
                    "offset": 366,
                    "line": 17,
                    "column": 20
                  },
                  "end": {
                    "offset": 396,
                    "line": 17,
                    "column": 50
                  },
                  "children": [
                    {
                      "kind": "EqualsGreaterThanToken",
                      "pos": {
                        "offset": 369,
                        "line": 17,
                        "column": 23
                      },
                      "end": {
                        "offset": 372,
                        "line": 17,
                        "column": 26
                      },
                      "text": "=>"
                    },
                    {
                      "kind": "ParenthesizedExpression",
                      "pos": {
                        "offset": 372,
                        "line": 17,
                        "column": 26
                      },
                      "end": {
                        "offset": 396,
                        "line": 17,
                        "column": 50
                      },
                      "children": [
                        {
                          "kind": "NullKeyword",
                          "pos": {
                            "offset": 391,
                            "line": 17,
                            "column": 45
                          },
                          "end": {
                            "offset": 395,
                            "line": 17,
                            "column": 49
                          },
                          "text": "null"
                        }
                      ]
                    }
                  ]
                }
              ]
            }
          ]
        }
      ]
    },
    {
      "kind": "ExpressionStatement",
      "pos": {
        "offset": 397,
        "line": 17,
        "column": 51
      },
      "end": {
        "offset": 451,
        "line": 21,
        "column": 3
      },
      "children": [
        {
          "kind": "BinaryExpression",
          "pos": {
            "offset": 397,
            "line": 17,
            "column": 51
          },
          "end": {
            "offset": 450,
            "line": 21,
            "column": 2
          },
          "children": [
            {
              "kind": "PropertyAccessExpression",
              "pos": {
                "offset": 397,
                "line": 17,
                "column": 51
              },
              "end": {
                "offset": 425,
                "line": 19,
                "column": 25
              },
              "children": [
                {
                  "kind": "Identifier",
                  "pos": {
                    "offset": 397,
                    "line": 17,
                    "column": 51
                  },
                  "end": {
                    "offset": 412,
                    "line": 19,
                    "column": 12
                  },
                  "text": "MyComponent"
                },
                {
                  "kind": "Identifier",
                  "pos": {
                    "offset": 413,
                    "line": 19,
                    "column": 13
                  },
                  "end": {
                    "offset": 425,
                    "line": 19,
                    "column": 25
                  },
                  "text": "defaultProps"
                }
              ]
            },
            {
              "kind": "FirstAssignment",
              "pos": {
                "offset": 425,
                "line": 19,
                "column": 25
              },
              "end": {
                "offset": 427,
                "line": 19,
                "column": 27
              },
              "text": "="
            },
            {
              "kind": "ObjectLiteralExpression",
              "pos": {
                "offset": 427,
                "line": 19,
                "column": 27
              },
              "end": {
                "offset": 450,
                "line": 21,
                "column": 2
              },
              "children": [
                {
                  "kind": "PropertyAssignment",
                  "pos": {
                    "offset": 429,
                    "line": 19,
                    "column": 29
                  },
                  "end": {
                    "offset": 447,
                    "line": 20,
                    "column": 17
                  },
                  "children": [
                    {
                      "kind": "Identifier",
                      "pos": {
                        "offset": 429,
                        "line": 19,
                        "column": 29
                      },
                      "end": {
                        "offset": 440,
                        "line": 20,
                        "column": 10
                      },
                      "text": "color"
                    },
                    {
                      "kind": "StringLiteral",
                      "pos": {
                        "offset": 441,
                        "line": 20,
                        "column": 11
                      },
                      "end": {
                        "offset": 447,
                        "line": 20,
                        "column": 17
                      },
                      "text": "red"
                    }
                  ]
                }
              ]
            }
          ]
        }
      ]
    },
    {
      "kind": "FirstStatement",
      "pos": {
        "offset": 451,
        "line": 21,
        "column": 3
      },
      "end": {
        "offset": 487,
        "line": 23,
        "column": 33
      },
      "children": [
        {
          "kind": "VariableDeclarationList",
          "pos": {
            "offset": 451,
            "line": 21,
            "column": 3
          },
          "end": {
            "offset": 486,
            "line": 23,
            "column": 32
          },
          "children": [
            {
              "kind": "VariableDeclaration",
              "pos": {
                "offset": 460,
                "line": 23,
                "column": 6
              },
              "end": {
                "offset": 486,
                "line": 23,
                "column": 32
              },
              "children": [
                {
                  "kind": "Identifier",
                  "pos": {
                    "offset": 460,
                    "line": 23,
                    "column": 6
                  },
                  "end": {
                    "offset": 473,
                    "line": 23,
                    "column": 19
                  },
                  "text": "MyComponent2"
                },
                {
                  "kind": "ArrowFunction",
                  "pos": {
                    "offset": 475,
                    "line": 23,
                    "column": 21
                  },
                  "end": {
                    "offset": 486,
                    "line": 23,
                    "column": 32
                  },
                  "children": [
                    {
                      "kind": "EqualsGreaterThanToken",
                      "pos": {
                        "offset": 478,
                        "line": 23,
                        "column": 24
                      },
                      "end": {
                        "offset": 481,
                        "line": 23,
                        "column": 27
                      },
                      "text": "=>"
                    },
                    {
                      "kind": "NullKeyword",
                      "pos": {
                        "offset": 481,
                        "line": 23,
                        "column": 27
                      },
                      "end": {
                        "offset": 486,
                        "line": 23,
                        "column": 32
                      },
                      "text": "null"
                    }
                  ]
                }
              ]
            }
          ]
        }
      ]
    },
    {
      "kind": "ExpressionStatement",
      "pos": {
        "offset": 487,
        "line": 23,
        "column": 33
      },
      "end": {
        "offset": 580,
        "line": 30,
        "column": 2
      },
      "children": [
        {
          "kind": "BinaryExpression",
          "pos": {
            "offset": 487,
            "line": 23,
            "column": 33
          },
          "end": {
            "offset": 580,
            "line": 30,
            "column": 2
          },
          "children": [
            {
              "kind": "PropertyAccessExpression",
              "pos": {
                "offset": 487,
                "line": 23,
                "column": 33
              },
              "end": {
                "offset": 555,
                "line": 28,
                "column": 26
              },
              "children": [
                {
                  "kind": "Identifier",
                  "pos": {
                    "offset": 487,
                    "line": 23,
                    "column": 33
                  },
                  "end": {
                    "offset": 542,
                    "line": 28,
                    "column": 13
                  },
                  "text": "MyComponent2"
                },
                {
                  "kind": "Identifier",
                  "pos": {
                    "offset": 543,
                    "line": 28,
                    "column": 14
                  },
                  "end": {
                    "offset": 555,
                    "line": 28,
                    "column": 26
                  },
                  "text": "defaultProps"
                }
              ]
            },
            {
              "kind": "FirstAssignment",
              "pos": {
                "offset": 555,
                "line": 28,
                "column": 26
              },
              "end": {
                "offset": 557,
                "line": 28,
                "column": 28
              },
              "text": "="
            },
            {
              "kind": "ObjectLiteralExpression",
              "pos": {
                "offset": 557,
                "line": 28,
                "column": 28
              },
              "end": {
                "offset": 580,
                "line": 30,
                "column": 2
              },
              "children": [
                {
                  "kind": "PropertyAssignment",
                  "pos": {
                    "offset": 559,
                    "line": 28,
                    "column": 30
                  },
                  "end": {
                    "offset": 577,
                    "line": 29,
                    "column": 17
                  },
                  "children": [
                    {
                      "kind": "Identifier",
                      "pos": {
                        "offset": 559,
                        "line": 28,
                        "column": 30
                      },
                      "end": {
                        "offset": 570,
                        "line": 29,
                        "column": 10
                      },
                      "text": "color"
                    },
                    {
                      "kind": "StringLiteral",
                      "pos": {
                        "offset": 571,
                        "line": 29,
                        "column": 11
                      },
                      "end": {
                        "offset": 577,
                        "line": 29,
                        "column": 17
                      },
                      "text": "red"
                    }
                  ]
                }
              ]
            }
          ]
        }
      ]
    },
    {
      "kind": "FirstStatement",
      "pos": {
        "offset": 580,
        "line": 30,
        "column": 2
      },
      "end": {
        "offset": 671,
        "line": 35,
        "column": 28
      },
      "children": [
        {
          "kind": "VariableDeclarationList",
          "pos": {
            "offset": 580,
            "line": 30,
            "column": 2
          },
          "end": {
            "offset": 670,
            "line": 35,
            "column": 27
          },
          "children": [
            {
              "kind": "VariableDeclaration",
              "pos": {
                "offset": 649,
                "line": 35,
                "column": 6
              },
              "end": {
                "offset": 670,
                "line": 35,
                "column": 27
              },
              "children": [
                {
                  "kind": "Identifier",
                  "pos": {
                    "offset": 649,
                    "line": 35,
                    "column": 6
                  },
                  "end": {
                    "offset": 655,
                    "line": 35,
                    "column": 12
                  },
                  "text": "check"
                },
                {
                  "kind": "Identifier",
                  "pos": {
                    "offset": 657,
                    "line": 35,
                    "column": 14
                  },
                  "end": {
                    "offset": 670,
                    "line": 35,
                    "column": 27
                  },
                  "text": "MyComponent2"
                }
              ]
            }
          ]
        }
      ]
    },
    {
      "kind": "FunctionDeclaration",
      "pos": {
        "offset": 671,
        "line": 35,
        "column": 28
      },
      "end": {
        "offset": 762,
        "line": 41,
        "column": 29
      },
      "children": [
        {
          "kind": "Identifier",
          "pos": {
            "offset": 742,
            "line": 41,
            "column": 9
          },
          "end": {
            "offset": 756,
            "line": 41,
            "column": 23
          },
          "text": "expectLiteral"
        },
        {
          "kind": "Parameter",
          "pos": {
            "offset": 757,
            "line": 41,
            "column": 24
          },
          "end": {
            "offset": 758,
            "line": 41,
            "column": 25
          },
          "children": [
            {
              "kind": "Identifier",
              "pos": {
                "offset": 757,
                "line": 41,
                "column": 24
              },
              "end": {
                "offset": 758,
                "line": 41,
                "column": 25
              },
              "text": "p"
            }
          ]
        },
        {
          "kind": "Block",
          "pos": {
            "offset": 759,
            "line": 41,
            "column": 26
          },
          "end": {
            "offset": 762,
            "line": 41,
            "column": 29
          }
        }
      ]
    },
    {
      "kind": "FunctionDeclaration",
      "pos": {
        "offset": 762,
        "line": 41,
        "column": 29
      },
      "end": {
        "offset": 900,
        "line": 50,
        "column": 2
      },
      "children": [
        {
          "kind": "Identifier",
          "pos": {
            "offset": 774,
            "line": 43,
            "column": 9
          },
          "end": {
            "offset": 778,
            "line": 43,
            "column": 13
          },
          "text": "foo"
        },
        {
          "kind": "Block",
          "pos": {
            "offset": 780,
            "line": 43,
            "column": 15
          },
          "end": {
            "offset": 900,
            "line": 50,
            "column": 2
          },
          "children": [
            {
              "kind": "ExpressionStatement",
              "pos": {
                "offset": 782,
                "line": 43,
                "column": 17
              },
              "end": {
                "offset": 869,
                "line": 47,
                "column": 35
              },
              "children": [
                {
                  "kind": "BinaryExpression",
                  "pos": {
                    "offset": 782,
                    "line": 43,
                    "column": 17
                  },
                  "end": {
                    "offset": 868,
                    "line": 47,
                    "column": 34
                  },
                  "children": [
                    {
                      "kind": "PropertyAccessExpression",
                      "pos": {
                        "offset": 782,
                        "line": 43,
                        "column": 17
                      },
                      "end": {
                        "offset": 849,
                        "line": 47,
                        "column": 15
                      },
                      "children": [
                        {
                          "kind": "ThisKeyword",
                          "pos": {
                            "offset": 782,
                            "line": 43,
                            "column": 17
                          },
                          "end": {
                            "offset": 843,
                            "line": 47,
                            "column": 9
                          },
                          "text": "this"
                        },
                        {
                          "kind": "Identifier",
                          "pos": {
                            "offset": 844,
                            "line": 47,
                            "column": 10
                          },
                          "end": {
                            "offset": 849,
                            "line": 47,
                            "column": 15
                          },
                          "text": "props"
                        }
                      ]
                    },
                    {
                      "kind": "FirstAssignment",
                      "pos": {
                        "offset": 849,
                        "line": 47,
                        "column": 15
                      },
                      "end": {
                        "offset": 851,
                        "line": 47,
                        "column": 17
                      },
                      "text": "="
                    },
                    {
                      "kind": "ObjectLiteralExpression",
                      "pos": {
                        "offset": 851,
                        "line": 47,
                        "column": 17
                      },
                      "end": {
                        "offset": 868,
                        "line": 47,
                        "column": 34
                      },
                      "children": [
                        {
                          "kind": "PropertyAssignment",
                          "pos": {
                            "offset": 853,
                            "line": 47,
                            "column": 19
                          },
                          "end": {
                            "offset": 866,
                            "line": 47,
                            "column": 32
                          },
                          "children": [
                            {
                              "kind": "Identifier",
                              "pos": {
                                "offset": 853,
                                "line": 47,
                                "column": 19
                              },
                              "end": {
                                "offset": 859,
                                "line": 47,
                                "column": 25
                              },
                              "text": "color"
                            },
                            {
                              "kind": "StringLiteral",
                              "pos": {
                                "offset": 860,
                                "line": 47,
                                "column": 26
                              },
                              "end": {
                                "offset": 866,
                                "line": 47,
                                "column": 32
                              },
                              "text": "red"
                            }
                          ]
                        }
                      ]
                    }
                  ]
                }
              ]
            },
            {
              "kind": "ExpressionStatement",
              "pos": {
                "offset": 869,
                "line": 47,
                "column": 35
              },
              "end": {
                "offset": 897,
                "line": 49,
                "column": 25
              },
              "children": [
                {
                  "kind": "CallExpression",
                  "pos": {
                    "offset": 869,
                    "line": 47,
                    "column": 35
                  },
                  "end": {
                    "offset": 896,
                    "line": 49,
                    "column": 24
                  },
                  "children": [
                    {
                      "kind": "Identifier",
                      "pos": {
                        "offset": 869,
                        "line": 47,
                        "column": 35
                      },
                      "end": {
                        "offset": 890,
                        "line": 49,
                        "column": 18
                      },
                      "text": "expectLiteral"
                    },
                    {
                      "kind": "ThisKeyword",
                      "pos": {
                        "offset": 891,
                        "line": 49,
                        "column": 19
                      },
                      "end": {
                        "offset": 895,
                        "line": 49,
                        "column": 23
                      },
                      "text": "this"
                    }
                  ]
                }
              ]
            }
          ]
        }
      ]
    },
    {
      "kind": "ExpressionStatement",
      "pos": {
        "offset": 900,
        "line": 50,
        "column": 2
      },
      "end": {
        "offset": 982,
        "line": 57,
        "column": 2
      },
      "children": [
        {
          "kind": "BinaryExpression",
          "pos": {
            "offset": 900,
            "line": 50,
            "column": 2
          },
          "end": {
            "offset": 982,
            "line": 57,
            "column": 2
          },
          "children": [
            {
              "kind": "PropertyAccessExpression",
              "pos": {
                "offset": 900,
                "line": 50,
                "column": 2
              },
              "end": {
                "offset": 957,
                "line": 55,
                "column": 15
              },
              "children": [
                {
                  "kind": "Identifier",
                  "pos": {
                    "offset": 900,
                    "line": 50,
                    "column": 2
                  },
                  "end": {
                    "offset": 949,
                    "line": 55,
                    "column": 7
                  },
                  "text": "module"
                },
                {
                  "kind": "Identifier",
                  "pos": {
                    "offset": 950,
                    "line": 55,
                    "column": 8
                  },
                  "end": {
                    "offset": 957,
                    "line": 55,
                    "column": 15
                  },
                  "text": "exports"
                }
              ]
            },
            {
              "kind": "FirstAssignment",
              "pos": {
                "offset": 957,
                "line": 55,
                "column": 15
              },
              "end": {
                "offset": 959,
                "line": 55,
                "column": 17
              },
              "text": "="
            },
            {
              "kind": "ObjectLiteralExpression",
              "pos": {
                "offset": 959,
                "line": 55,
                "column": 17
              },
              "end": {
                "offset": 982,
                "line": 57,
                "column": 2
              },
              "children": [
                {
                  "kind": "PropertyAssignment",
                  "pos": {
                    "offset": 961,
                    "line": 55,
                    "column": 19
                  },
                  "end": {
                    "offset": 979,
                    "line": 56,
                    "column": 17
                  },
                  "children": [
                    {
                      "kind": "Identifier",
                      "pos": {
                        "offset": 961,
                        "line": 55,
                        "column": 19
                      },
                      "end": {
                        "offset": 972,
                        "line": 56,
                        "column": 10
                      },
                      "text": "color"
                    },
                    {
                      "kind": "StringLiteral",
                      "pos": {
                        "offset": 973,
                        "line": 56,
                        "column": 11
                      },
                      "end": {
                        "offset": 979,
                        "line": 56,
                        "column": 17
                      },
                      "text": "red"
                    }
                  ]
                }
              ]
            }
          ]
        }
      ]
    },
    {
      "kind": "ExpressionStatement",
      "pos": {
        "offset": 982,
        "line": 57,
        "column": 2
      },
      "end": {
        "offset": 1027,
        "line": 59,
        "column": 42
      },
      "children": [
        {
          "kind": "CallExpression",
          "pos": {
            "offset": 982,
            "line": 57,
            "column": 2
          },
          "end": {
            "offset": 1026,
            "line": 59,
            "column": 41
          },
          "children": [
            {
              "kind": "Identifier",
              "pos": {
                "offset": 982,
                "line": 57,
                "column": 2
              },
              "end": {
                "offset": 999,
                "line": 59,
                "column": 14
              },
              "text": "expectLiteral"
            },
            {
              "kind": "ObjectLiteralExpression",
              "pos": {
                "offset": 1000,
                "line": 59,
                "column": 15
              },
              "end": {
                "offset": 1025,
                "line": 59,
                "column": 40
              },
              "children": [
                {
                  "kind": "PropertyAssignment",
                  "pos": {
                    "offset": 1001,
                    "line": 59,
                    "column": 16
                  },
                  "end": {
                    "offset": 1023,
                    "line": 59,
                    "column": 38
                  },
                  "children": [
                    {
                      "kind": "Identifier",
                      "pos": {
                        "offset": 1001,
                        "line": 59,
                        "column": 16
                      },
                      "end": {
                        "offset": 1007,
                        "line": 59,
                        "column": 22
                      },
                      "text": "props"
                    },
                    {
                      "kind": "PropertyAccessExpression",
                      "pos": {
                        "offset": 1008,
                        "line": 59,
                        "column": 23
                      },
                      "end": {
                        "offset": 1023,
                        "line": 59,
                        "column": 38
                      },
                      "children": [
                        {
                          "kind": "Identifier",
                          "pos": {
                            "offset": 1008,
                            "line": 59,
                            "column": 23
                          },
                          "end": {
                            "offset": 1015,
                            "line": 59,
                            "column": 30
                          },
                          "text": "module"
                        },
                        {
                          "kind": "Identifier",
                          "pos": {
                            "offset": 1016,
                            "line": 59,
                            "column": 31
                          },
                          "end": {
                            "offset": 1023,
                            "line": 59,
                            "column": 38
                          },
                          "text": "exports"
                        }
                      ]
                    }
                  ]
                }
              ]
            }
          ]
        }
      ]
    },
    {
      "kind": "EndOfFileToken",
      "pos": {
        "offset": 1027,
        "line": 59,
        "column": 42
      },
      "end": {
        "offset": 1029,
        "line": 60,
        "column": 1
      },
      "text": ""
    }
  ]
}
